text_importer/__init__.py
text_importer/tokenization.py
text_importer/utils.py
text_importer/importers/__init__.py
text_importer/importers/classes.py
text_importer/importers/core.py
text_importer/importers/generic_importer.py
text_importer/importers/bcul/__init__.py
text_importer/importers/bcul/classes.py
text_importer/importers/bcul/detect.py
text_importer/importers/bcul/helpers.py
text_importer/importers/bl/__init__.py
text_importer/importers/bl/classes.py
text_importer/importers/bl/detect.py
text_importer/importers/bnf/__init__.py
text_importer/importers/bnf/classes.py
text_importer/importers/bnf/detect.py
text_importer/importers/bnf/helpers.py
text_importer/importers/bnf/parsers.py
text_importer/importers/bnf_en/__init__.py
text_importer/importers/bnf_en/classes.py
text_importer/importers/bnf_en/detect.py
text_importer/importers/fedgaz/__init__.py
text_importer/importers/fedgaz/classes.py
text_importer/importers/fedgaz/show_canonical_boxes.py
text_importer/importers/lux/__init__.py
text_importer/importers/lux/classes.py
text_importer/importers/lux/detect.py
text_importer/importers/lux/helpers.py
text_importer/importers/lux/test_dask_memory.py
text_importer/importers/mets_alto/__init__.py
text_importer/importers/mets_alto/alto.py
text_importer/importers/mets_alto/classes.py
text_importer/importers/mets_alto/mets.py
text_importer/importers/olive/__init__.py
text_importer/importers/olive/classes.py
text_importer/importers/olive/detect.py
text_importer/importers/olive/helpers.py
text_importer/importers/olive/parsers.py
text_importer/importers/onb_annop/__init__.py
text_importer/importers/onb_annop/classes.py
text_importer/importers/onb_annop/detect.py
text_importer/importers/rero/__init__.py
text_importer/importers/rero/classes.py
text_importer/importers/rero/detect.py
text_importer/importers/swa/__init__.py
text_importer/importers/swa/classes.py
text_importer/importers/swa/detect.py
text_importer/importers/tetml/__init__.py
text_importer/importers/tetml/classes.py
impresso_text_importer-1.2.0.dist-info/LICENSE
impresso_text_importer-1.2.0.dist-info/METADATA
impresso_text_importer-1.2.0.dist-info/WHEEL
impresso_text_importer-1.2.0.dist-info/entry_points.txt
impresso_text_importer-1.2.0.dist-info/top_level.txt
impresso_text_importer-1.2.0.dist-info/RECORD
