Metadata-Version: 2.1
Name: impresso_text_importer
Version: 1.2.0
Summary: Library to import newspaper data from a variety of OCR formats into Impresso's JSON format.
Author-email: Maud Ehrmann <maud.ehrmann@epfl.ch>, Matteo Romanello <matteo.romanello@gmail.com>, Pauline Conti <pauline.conti@epfl.ch>
License: GNU AFFERO GENERAL PUBLIC LICENSE
Project-URL: Homepage, https://github.com/impresso/impresso-text-acquisition
Project-URL: Documentaton, https://impresso-text-importer.readthedocs.io/en/latest/index.html
Classifier: Programming Language :: Python :: 3
Classifier: Intended Audience :: Developers
Classifier: Intended Audience :: Science/Research
Classifier: License :: OSI Approved :: GNU Affero General Public License v3 or later (AGPLv3+)
Classifier: Operating System :: OS Independent
Classifier: Programming Language :: Python :: 3 :: Only
Classifier: Programming Language :: Python :: 3.10
Classifier: Programming Language :: Python :: 3.11
Requires-Python: >=3.10
License-File: LICENSE
Requires-Dist: beautifulsoup4
Requires-Dist: docopt
Requires-Dist: pandas
Requires-Dist: dask[complete]
Requires-Dist: lxml
Requires-Dist: python-jsonschema-objects
Requires-Dist: regex
Requires-Dist: filelock
Requires-Dist: impresso-commons
